sparkfly/__init__.py
sparkfly/api_client.py
sparkfly/api_response.py
sparkfly/client.py
sparkfly/configuration.py
sparkfly/exceptions.py
sparkfly/py.typed
sparkfly/rest.py
sparkfly/api/__init__.py
sparkfly/api/audiences_api.py
sparkfly/api/authentication_api.py
sparkfly/api/bi_store_lists_api.py
sparkfly/api/campaigns_api.py
sparkfly/api/credentials_api.py
sparkfly/api/ctm_api.py
sparkfly/api/eligible_item_sets_api.py
sparkfly/api/email_opt_in_api.py
sparkfly/api/event_notifications_api.py
sparkfly/api/impressions_api.py
sparkfly/api/items_api.py
sparkfly/api/member_privacy_api.py
sparkfly/api/members_api.py
sparkfly/api/offer_lists_api.py
sparkfly/api/offer_pos_offer_codes_api.py
sparkfly/api/offer_states_api.py
sparkfly/api/offers_api.py
sparkfly/api/pos_offer_codes_api.py
sparkfly/api/store_lists_api.py
sparkfly/api/stores_api.py
sparkfly/api/templates_api.py
sparkfly/api/transactions_api.py
sparkfly/models/__init__.py
sparkfly/models/api_error.py
sparkfly/models/atomic_member_create_body.py
sparkfly/models/atomic_member_create_body_member.py
sparkfly/models/atomic_member_create_body_member_credentials_inner.py
sparkfly/models/atomic_member_create_body_member_credentials_inner_credential.py
sparkfly/models/atomic_member_create_body_member_loyalty_enrollments_inner.py
sparkfly/models/atomic_member_create_body_member_loyalty_enrollments_inner_loyalty_enrollment.py
sparkfly/models/atomic_member_create_body_member_member_profile.py
sparkfly/models/atomic_member_response_body.py
sparkfly/models/atomic_member_response_body_member.py
sparkfly/models/atomic_member_response_body_member_credentials_inner.py
sparkfly/models/atomic_member_response_body_member_credentials_inner_credential.py
sparkfly/models/atomic_member_response_body_member_loyalty_enrollments_inner.py
sparkfly/models/atomic_member_response_body_member_loyalty_enrollments_inner_loyalty_enrollment.py
sparkfly/models/atomic_member_response_body_member_member_profile.py
sparkfly/models/audience.py
sparkfly-1.3.7.dist-info/licenses/LICENSE
sparkfly-1.3.7.dist-info/METADATA
sparkfly-1.3.7.dist-info/WHEEL
sparkfly-1.3.7.dist-info/top_level.txt
sparkfly-1.3.7.dist-info/RECORD
