Metadata-Version: 2.4
Name: sparkfly
Version: 1.3.7
Summary: Core Operations
Home-page: https://github.com/growth-operations/sparkfly-api-client
Author: Sparkfly Support Team
Author-email: Growth Operations Support Team <info@growthoperationsco.com>
License: MIT
Project-URL: Repository, https://github.com/growth-operations/sparkfly-api-client
Keywords: OpenAPI,OpenAPI-Generator,Core Operations
Requires-Python: >=3.9
License-File: LICENSE
Requires-Dist: urllib3<3.0.0,>=2.1.0
Requires-Dist: python-dateutil>=2.8.2
Requires-Dist: aiohttp>=3.8.4
Requires-Dist: aiohttp-retry>=2.8.3
Requires-Dist: pydantic>=2
Requires-Dist: typing-extensions>=4.7.1
Dynamic: author
Dynamic: home-page
Dynamic: license-file
